git_stacky/__init__.py
git_stacky/cli.py
git_stacky-0.10.0.dist-info/METADATA
git_stacky-0.10.0.dist-info/WHEEL
git_stacky-0.10.0.dist-info/entry_points.txt
git_stacky-0.10.0.dist-info/RECORD
