Metadata-Version: 2.1
Name: git_stacky
Version: 0.10.0
Summary: Minimal Git extension for working with multi-commit stacks
Author: Hunter Gatewood
Author-email: hgatewood@gmail.com
Requires-Python: >=3.12,<4.0
Classifier: Programming Language :: Python :: 3
Classifier: Programming Language :: Python :: 3.12
Requires-Dist: click (>=8.0.0,<9.0.0)
